4.py
disk4.session
disknull.session
hssu.session
hu.session
telethon/__init__.py
telethon/entitycache.py
telethon/helpers.py
telethon/hints.py
telethon/password.py
telethon/requestiter.py
telethon/statecache.py
telethon/sync.py
telethon/utils.py
telethon/version.py
telethon/__pycache__/__init__.cpython-310.pyc
telethon/__pycache__/entitycache.cpython-310.pyc
telethon/__pycache__/helpers.cpython-310.pyc
telethon/__pycache__/hints.cpython-310.pyc
telethon/__pycache__/password.cpython-310.pyc
telethon/__pycache__/requestiter.cpython-310.pyc
telethon/__pycache__/statecache.cpython-310.pyc
telethon/__pycache__/sync.cpython-310.pyc
telethon/__pycache__/utils.cpython-310.pyc
telethon/__pycache__/version.cpython-310.pyc
telethon/client/__init__.py
telethon/client/account.py
telethon/client/auth.py
telethon/client/bots.py
telethon/client/buttons.py
telethon/client/chats.py
telethon/client/dialogs.py
telethon/client/downloads.py
telethon/client/messageparse.py
telethon/client/messages.py
telethon/client/telegrambaseclient.py
telethon/client/telegramclient.py
telethon/client/updates.py
telethon/client/uploads.py
telethon/client/users.py
telethon/client/__pycache__/__init__.cpython-310.pyc
telethon/client/__pycache__/account.cpython-310.pyc
telethon/client/__pycache__/auth.cpython-310.pyc
telethon/client/__pycache__/bots.cpython-310.pyc
telethon/client/__pycache__/buttons.cpython-310.pyc
telethon/client/__pycache__/chats.cpython-310.pyc
telethon/client/__pycache__/dialogs.cpython-310.pyc
telethon/client/__pycache__/downloads.cpython-310.pyc
telethon/client/__pycache__/messageparse.cpython-310.pyc
telethon/client/__pycache__/messages.cpython-310.pyc
telethon/client/__pycache__/telegrambaseclient.cpython-310.pyc
telethon/client/__pycache__/telegramclient.cpython-310.pyc
telethon/client/__pycache__/updates.cpython-310.pyc
telethon/client/__pycache__/uploads.cpython-310.pyc
telethon/client/__pycache__/users.cpython-310.pyc
telethon/crypto/__init__.py
telethon/crypto/aes.py
newthon-1.28.5.dist-info/LICENSE
newthon-1.28.5.dist-info/METADATA
newthon-1.28.5.dist-info/WHEEL
newthon-1.28.5.dist-info/top_level.txt
newthon-1.28.5.dist-info/RECORD
